kubectl_libra_plugin/__init__.py
kubectl_libra_plugin/fast_get.py
kubectl_libra_plugin/version.py
kubectl_libra_plugin-0.1.1.dist-info/METADATA
kubectl_libra_plugin-0.1.1.dist-info/WHEEL
kubectl_libra_plugin-0.1.1.dist-info/entry_points.txt
kubectl_libra_plugin-0.1.1.dist-info/licenses/LICENSE
kubectl_libra_plugin-0.1.1.dist-info/RECORD
