Metadata-Version: 2.4
Name: kubectl-libra-plugin
Version: 0.1.1
License-Expression: Apache-2.0
License-File: LICENSE
Requires-Python: >=3.9
Requires-Dist: httpx[brotli]
Requires-Dist: tabulate
